__init__.py
pueblo_goof/__init__.py
pueblo_goof/cli.py
pueblo_goof/util.py
pueblo_goof/slack/__init__.py
pueblo_goof/slack/conversation.py
pueblo_goof/slack/model.py
rapporto/__init__.py
rapporto/cli.py
rapporto/option.py
rapporto/util.py
rapporto/animate/__init__.py
rapporto/animate/cli.py
rapporto/animate/git.py
rapporto/notify/__init__.py
rapporto/notify/cli.py
rapporto/notify/slack.py
rapporto/report/__init__.py
rapporto/report/cli.py
rapporto/report/model.py
rapporto/source/__init__.py
rapporto/source/changes/__init__.py
rapporto/source/changes/cli.py
rapporto/source/changes/core.py
rapporto/source/changes/util.py
rapporto/source/github/__init__.py
rapporto/source/github/actions.py
rapporto/source/github/activity.py
rapporto/source/github/attention.py
rapporto/source/github/backup.py
rapporto/source/github/cli.py
rapporto/source/github/model.py
rapporto/source/github/util.py
rapporto/source/opsgenie/__init__.py
rapporto/source/opsgenie/cli.py
rapporto/source/opsgenie/core.py
rapporto/source/slack/__init__.py
rapporto/source/slack/cli.py
rapporto/source/slack/core.py
rapporto-0.6.1.dist-info/licenses/LICENSE
rapporto-0.6.1.dist-info/METADATA
rapporto-0.6.1.dist-info/WHEEL
rapporto-0.6.1.dist-info/entry_points.txt
rapporto-0.6.1.dist-info/top_level.txt
rapporto-0.6.1.dist-info/RECORD
